{
  "livro": "Proverbios",
  "abbrev": "pv",
  "capitulo": 9,
  "total_capitulos": 31,
  "total_versiculos": 17,
  "fonte": "Biblia Pastoral — Ed. Paulus",
  "versiculos": [
    {
      "number": 1,
      "text": "A Sabedoria construiu a sua casa, talhando suas sete colunas."
    },
    {
      "number": 2,
      "text": "Abateu seus animais, preparou o vinho e pôs a mesa."
    },
    {
      "number": 3,
      "text": "Enviou suas criadas para anunciar nos pontos mais altos da cidade:"
    },
    {
      "number": 4,
      "text": "“Os ingênuos venham até aqui. Quero falar aos que não têm juízo."
    },
    {
      "number": 5,
      "text": "Venham comer do meu pão e beber do vinho que eu preparei."
    },
    {
      "number": 6,
      "text": "Deixem de ser ingênuos, e vocês viverão; sigam o caminho da inteligência”."
    },
    {
      "number": 7,
      "text": "Quem corrige o zombador, atrai o seu desprezo; e quem repreende o injusto, atrai o insulto."
    },
    {
      "number": 8,
      "text": "Não repreenda o zombador, porque ele odiará você. Repreenda o sábio, pois ele lhe agradecerá."
    },
    {
      "number": 9,
      "text": "Dê um conselho ao sábio, e ele se tornará mais sábio ainda. Dê instrução ao justo, e ele aprenderá ainda mais."
    },
    {
      "number": 10,
      "text": "O princípio da sabedoria é o temor de Javé, e conhecer o Santo é inteligência."
    },
    {
      "number": 11,
      "text": "Por meio de mim, você prolongará os seus dias, e terá mais anos de vida."
    },
    {
      "number": 12,
      "text": "Se você for sensato, a vantagem será sua; se for zombador, o azar será seu."
    },
    {
      "number": 13,
      "text": "A senhora Insensatez é irrequieta, é uma ingênua que não conhece nada."
    },
    {
      "number": 14,
      "text": "Ela fica sentada na porta da casa, num banco de onde domina a cidade."
    },
    {
      "number": 15,
      "text": "Daí, ela chama os que passam e que vão seguindo pelo caminho reto:"
    },
    {
      "number": 16,
      "text": "“Os ingênuos venham aqui. Quero falar aos que não têm juízo."
    },
    {
      "number": 17,
      "text": "A água roubada é mais doce, e o pão comido às escondidas é mais gostoso”."
    }
  ]
}