{
  "livro": "Salmos",
  "abbrev": "sl",
  "capitulo": 100,
  "total_capitulos": 150,
  "total_versiculos": 4,
  "fonte": "Biblia Pastoral — Ed. Paulus",
  "versiculos": [
    {
      "number": 1,
      "text": "Salmo. Para ação de graças. Terra inteira, aclame a Javé!"
    },
    {
      "number": 2,
      "text": "Sirva a Javé com alegria, e vá até ele com gritos jubilosos!"
    },
    {
      "number": 3,
      "text": "Saiba que somente Javé é Deus: Ele nos fez e a ele pertencemos, somos seu povo e ovelhas do seu rebanho."
    },
    {
      "number": 4,
      "text": "Entrem por suas portas dando graças, com cantos de louvor em seus átrios, celebrem a ele e bendigam o seu nome:"
    }
  ]
}