{
  "livro": "Salmos",
  "abbrev": "sl",
  "capitulo": 20,
  "total_capitulos": 150,
  "total_versiculos": 9,
  "fonte": "Biblia Pastoral — Ed. Paulus",
  "versiculos": [
    {
      "number": 1,
      "text": "Do mestre de canto. Salmo. De Davi."
    },
    {
      "number": 2,
      "text": "Que Javé lhe responda no dia da angústia, que o nome do Deus de Jacó o proteja!"
    },
    {
      "number": 3,
      "text": "Que do santuário ele mande socorro para você, e o apóie desde Sião!"
    },
    {
      "number": 4,
      "text": "Que ele se lembre de suas ofertas todas, e aprecie o seu holocausto!"
    },
    {
      "number": 5,
      "text": "Que lhe dê tudo o que o seu coração deseja, e realize todos os seus projetos!"
    },
    {
      "number": 6,
      "text": "Possamos alegrar-nos com a sua vitória, e hastear a bandeira em nome do nosso Deus! Que Javé realize todos os seus pedidos!"
    },
    {
      "number": 7,
      "text": "Agora reconheço que Javé dá a vitória ao seu ungido, e lhe responde do seu templo celeste com os prodígios de sua mão vitoriosa."
    },
    {
      "number": 8,
      "text": "Uns confiam em carros, outros em cavalos; quanto a nós, invocamos o nome de Javé nosso Deus."
    },
    {
      "number": 9,
      "text": "Eles se curvam e caem; nós nos mantemos de pé."
    }
  ]
}