{
  "livro": "Salmos",
  "abbrev": "sl",
  "capitulo": 27,
  "total_capitulos": 150,
  "total_versiculos": 13,
  "fonte": "Biblia Pastoral — Ed. Paulus",
  "versiculos": [
    {
      "number": 1,
      "text": "De Davi. Javé é minha luz e salvação: de quem terei medo? Javé é a fortaleza da minha vida: frente a quem tremerei?"
    },
    {
      "number": 2,
      "text": "Quando os malfeitores avançam contra mim para devorar minha carne, são eles, meus adversários e inimigos, que tropeçam e caem."
    },
    {
      "number": 3,
      "text": "Que um exército acampe contra mim! Meu coração não tremerá! Que uma guerra estoure contra mim! Ainda assim estarei confiante!"
    },
    {
      "number": 4,
      "text": "Uma coisa peço a Javé, e só esta procuro: é habitar na casa de Javé todos os dias de minha vida, para gozar a doçura de Javé e contemplar o seu templo."
    },
    {
      "number": 5,
      "text": "Pois ele me oculta na sua cabana, no dia da infelicidade; ele me esconde no segredo de sua tenda, e me eleva sobre uma rocha."
    },
    {
      "number": 6,
      "text": "Agora minha cabeça se levanta sobre os inimigos que me cercam. Na tenda de Javé vou oferecer sacrifícios de aclamação. Vou cantar, vou tocar em honra de Javé!"
    },
    {
      "number": 7,
      "text": "Javé, escuta meu grito de apelo, tem piedade, responde-me!"
    },
    {
      "number": 8,
      "text": "Ouço no meu coração: “Procurem minha face!” — É tua face que eu procuro, Javé."
    },
    {
      "number": 9,
      "text": "Não me escondas a tua face. Não afastes teu servo com ira, pois tu és o meu socorro! Não me deixes, não me abandones, meu Deus salvador!"
    },
    {
      "number": 10,
      "text": "Meu pai e minha mãe me abandonaram. Javé, porém, me acolhe!"
    },
    {
      "number": 11,
      "text": "Ensina-me o teu caminho, Javé! Guia-me pela vereda plana, por causa daqueles que me espreitam."
    },
    {
      "number": 12,
      "text": "Não me entregues à vontade dos meus adversários, pois contra mim falsas testemunhas se levantam, respirando violência."
    },
    {
      "number": 13,
      "text": "Espero ver a bondade de Javé na terra dos vivos."
    }
  ]
}