{
  "livro": "Salmos",
  "abbrev": "sl",
  "capitulo": 60,
  "total_capitulos": 150,
  "total_versiculos": 13,
  "fonte": "Biblia Pastoral — Ed. Paulus",
  "versiculos": [
    {
      "number": 1,
      "text": "Do mestre de canto. Sobre “O lírio é o preceito”. À meia-voz. De Davi. Para ensinar."
    },
    {
      "number": 2,
      "text": "Quando ele lutou contra os arameus da Mesopotâmia e os arameus de Soba, e quando Joab voltou e derrotou Edom, cerca de doze mil homens, no Vale do Sal."
    },
    {
      "number": 3,
      "text": "Ó Deus, tu nos rejeitaste e dispersaste. Estavas irritado. Restaura-nos!"
    },
    {
      "number": 4,
      "text": "Fizeste a terra tremer e a fendeste. Repara suas fendas, pois ela vacila!"
    },
    {
      "number": 5,
      "text": "Mostraste duras coisas ao teu povo, e nos fizeste beber um vinho estonteante."
    },
    {
      "number": 6,
      "text": "Deste aos teus fiéis o sinal de retirada, para que fugissem diante dos arcos."
    },
    {
      "number": 7,
      "text": "Para que teus amados sejam libertos, a tua mão salvadora responda para nós!"
    },
    {
      "number": 8,
      "text": "Deus falou em seu santuário: “Triunfante ocuparei Siquém, e repartirei o vale de Sucot."
    },
    {
      "number": 9,
      "text": "Meu é Galaad, meu é Manassés, Efraim é o elmo da minha cabeça, Judá, o meu cetro de comando."
    },
    {
      "number": 10,
      "text": "Moab é a bacia onde me lavo. Sobre Edom atiro a minha sandália, e sobre a Filisteia canto vitória”."
    },
    {
      "number": 11,
      "text": "Quem me levará a uma cidade-forte, quem me conduzirá até Edom,"
    },
    {
      "number": 12,
      "text": "se tu, ó Deus, nos rejeitaste, e já não acompanhas nossas tropas?"
    },
    {
      "number": 13,
      "text": "Concede-nos socorro na opressão, pois o auxílio humano é inútil!"
    }
  ]
}