{
  "livro": "Salmos",
  "abbrev": "sl",
  "capitulo": 88,
  "total_capitulos": 150,
  "total_versiculos": 18,
  "fonte": "Biblia Pastoral — Ed. Paulus",
  "versiculos": [
    {
      "number": 1,
      "text": "Cântico. Salmo. Dos filhos de Coré. Do mestre de canto. Para a doença. Para a aflição. Poema. De Emã, o ezraíta."
    },
    {
      "number": 2,
      "text": "Javé meu Deus, de dia eu te peço auxílio, e de noite eu grito em tua presença."
    },
    {
      "number": 3,
      "text": "Que minha prece chegue a ti, inclina teu ouvido ao meu clamor."
    },
    {
      "number": 4,
      "text": "Porque minha alma está cheia de males, e minha vida está à beira do túmulo."
    },
    {
      "number": 5,
      "text": "Sou visto como quem baixa para a cova, tornei-me homem sem forças,"
    },
    {
      "number": 6,
      "text": "tenho minha cama entre os mortos, como as vítimas que jazem no sepulcro, das quais já não te lembras, porque foram arrancadas de tua mão."
    },
    {
      "number": 7,
      "text": "Jogaste-me no fundo da cova, em meio às trevas do abismo."
    },
    {
      "number": 8,
      "text": "Tua cólera pesa sobre mim, derramas sobre mim tuas ondas todas."
    },
    {
      "number": 9,
      "text": "Afastaste de mim meus conhecidos, e me tornaste repugnante para eles: estou fechado, não posso sair,"
    },
    {
      "number": 10,
      "text": "e meus olhos se turvam de tristeza. Eu te invoco o dia todo, estendendo as mãos para ti:"
    },
    {
      "number": 11,
      "text": "“Farás maravilhas pelos mortos? As sombras se levantarão para te louvar?"
    },
    {
      "number": 12,
      "text": "Falarão do teu amor nas sepulturas e da tua fidelidade no reino da morte?"
    },
    {
      "number": 13,
      "text": "Conhecem tuas maravilhas na treva e a tua justiça na terra do esquecimento?”"
    },
    {
      "number": 14,
      "text": "Mas eu grito para ti, Javé, minha prece chega a ti pela manhã."
    },
    {
      "number": 15,
      "text": "Javé, por que me rejeitas e escondes de mim a tua face?"
    },
    {
      "number": 16,
      "text": "Fui infeliz e moribundo desde a infância, sofri teus horrores, estou esgotado."
    },
    {
      "number": 17,
      "text": "Teus furores passaram sobre mim, teus terrores me deixaram consumido."
    },
    {
      "number": 18,
      "text": "Eles me cercam como água o dia todo, e todos juntos me envolvem de uma vez."
    }
  ]
}