{
  "livro": "Jo",
  "abbrev": "jo",
  "capitulo": 39,
  "total_capitulos": 42,
  "total_versiculos": 33,
  "fonte": "Biblia Pastoral — Ed. Paulus",
  "versiculos": [
    {
      "number": 1,
      "text": "Você sabe quando é que as camurças dão cria? Já assistiu o parto das corças?"
    },
    {
      "number": 2,
      "text": "Você conta os meses de gravidez delas ou conhece o momento do parto?"
    },
    {
      "number": 3,
      "text": "Elas se agacham, dão cria e se livram das dores."
    },
    {
      "number": 4,
      "text": "Os filhotes crescem e ficam fortes, saem para o campo aberto e não voltam mais."
    },
    {
      "number": 5,
      "text": "Quem dá liberdade ao asno selvagem e solta as rédeas do burro xucro,"
    },
    {
      "number": 6,
      "text": "ao qual dei o deserto como habitação e a planície salgada como moradia?"
    },
    {
      "number": 7,
      "text": "Ele se ri do barulho da cidade e não dá atenção aos xingos de quem o arreia."
    },
    {
      "number": 8,
      "text": "Ele explora as montanhas em busca de pasto, à procura de lugares verdes."
    },
    {
      "number": 9,
      "text": "Será que o búfalo aceita servir a você e passar a noite em seu estábulo?"
    },
    {
      "number": 10,
      "text": "Você pode colocar nele uma canga, para que ele are a terra atrás de você?"
    },
    {
      "number": 11,
      "text": "Ele é forte. Mas será que você pode confiar nele para fazer o seu trabalho?"
    },
    {
      "number": 12,
      "text": "Você pode contar com ele, para que volte e venha moer o grão no terreiro?"
    },
    {
      "number": 13,
      "text": "O avestruz bate asas alegremente, como se tivesse penas e plumas de cegonha."
    },
    {
      "number": 14,
      "text": "Ele deixa seus ovos no chão, para chocá-los na areia,"
    },
    {
      "number": 15,
      "text": "sem pensar que algum pé poderá quebrá-los ou serem pisados por alguma fera."
    },
    {
      "number": 16,
      "text": "Ele é cruel com os filhotes, como se não fossem seus, e não se importa com a inútil fadiga deles,"
    },
    {
      "number": 17,
      "text": "porque Deus o privou de sabedoria e não lhe concedeu inteligência."
    },
    {
      "number": 18,
      "text": "Contudo, quando se levanta batendo os flancos, ele se ri de cavalos e cavaleiros."
    },
    {
      "number": 19,
      "text": "Você pode dar força ao cavalo e vestir de crina o pescoço dele?"
    },
    {
      "number": 20,
      "text": "Você o ensina a saltar como um gafanhoto, relinchando com majestade e terror?"
    },
    {
      "number": 21,
      "text": "Cheio de força, ele pateia o chão e se lança ao encontro das armas."
    },
    {
      "number": 22,
      "text": "Ele ri do medo, não se assusta e diante da espada não volta para trás."
    },
    {
      "number": 23,
      "text": "Sobre ele ressoam o barulho do escudo, a lança faiscante e o dardo."
    },
    {
      "number": 24,
      "text": "Com ímpeto e estrondo, ele devora a distância e não pára, mesmo que soe o clarim."
    },
    {
      "number": 25,
      "text": "Ao toque da trombeta, ele relincha; fareja de longe a batalha, as ordens de comando e os gritos de guerra."
    },
    {
      "number": 26,
      "text": "Será pela sabedoria que você tem, que o falcão levanta voo, estendendo as asas para o sul?"
    },
    {
      "number": 27,
      "text": "Por acaso é com sua ordem que a águia levanta voo e constrói seu ninho nas alturas?"
    },
    {
      "number": 28,
      "text": "Ela mora nos rochedos, e aí pernoita numa fortaleza de rocha inatingível."
    },
    {
      "number": 29,
      "text": "Do alto ela espia a sua presa; seus olhos a enxergam de longe."
    },
    {
      "number": 30,
      "text": "Seus filhotes bebem o sangue, e onde há cadáveres ela aí está”. Gerar Imagem Gerador de imagem Católica &times; Texto selecionado: Nenhum texto selecionado Configuração da Fonte: Tamanho Tipo Cor Tamanho da Fonte: 50px 20px 100px Escolha o Tipo de Fonte: Georgia Times New Roman Palatino Linotype Garamond Book Antiqua Baskerville Hoefler Text Bodoni MT Didot Cambria Playfair Display Merriweather Lora Crimson Text Libre Baskerville EB Garamond Cormorant Garamond Spectral Roboto Open Sans Lato Montserrat Poppins Raleway Nunito Work Sans Inter Quicksand Josefin Sans Arial Helvetica Trebuchet MS Verdana Tahoma Lucida Sans Calibri Century Gothic Futura Dancing Script Pacifico Great Vibes Satisfy Caveat Brush Script MT Comic Sans MS Courier New Lucida Console Monaco Consolas Source Code Pro Impact Bebas Neue Righteous Abril Fatface Cinzel Escolha entre diferentes estilos de fontes Escolha a Cor do Texto: #FFFFFF Branco Cores Rápidas Cor Personalizada Tons de Cinza Clique no seletor acima para escolher uma cor Dimensões da Imagem: Padrão (800x600) Instagram Quadrado (1080x1080) Instagram Story (1080x1350) Facebook/Twitter (1200x630) Full HD (1920x1080) Tipo de Background: Imagens Gradientes Cor Sólida Uma imagem aleatória será selecionada automaticamente Escolha um Gradiente: Roxo Profundo Índigo → Roxo Gradientes Vibrantes Gradientes Suaves Gradientes Quentes Clique no seletor acima para escolher um gradiente Escolha uma Cor Sólida: #3949AB Azul Índigo Cores Vibrantes Cores Suaves Cor Personalizada Tons de Cinza Clique no seletor acima para escolher uma cor Ou Envie sua Imagem: Escolher Arquivo Baixar Imagem Compartilhar"
    },
    {
      "number": 39,
      "text": "- Bíblia Católica Pastoral - Ed. Paulus | Lírio Católico Jó"
    },
    {
      "number": 40,
      "text": "Início da Bíblia Selecionar livro... Gênesis Êxodo Levítico Números Deuteronômio Josué Juízes Rute I Samuel II Samuel I Reis II Reis I Crônicas II Crônicas Esdras Neemias Tobias Judite Ester I Macabeus II Macabeus Jó Salmos Provérbios Eclesiastes Cântico dos Cânticos Sabedoria Eclesiástico Isaías Jeremias Lamentações Baruc Ezequiel Daniel Oséias Joel Amós Abdias Jonas Miquéias Naum Habacuc Sofonias Ageu Zacarias Malaquias São Mateus São Marcos São Lucas São João Atos dos Apóstolos Romanos I Coríntios II Coríntios Gálatas Efésios Filipenses Colossenses I Tessalonicenses II Tessalonicenses I Timóteo II Timóteo Tito Filêmon Hebreus São Tiago I São Pedro II São Pedro I São João II São João III São João São Judas Apocalipse Selecionar capítulo... Capítulo"
    },
    {
      "number": 42,
      "text": "Ler Jo completo"
    }
  ]
}