{
  "livro": "Jo",
  "abbrev": "jo",
  "capitulo": 5,
  "total_capitulos": 42,
  "total_versiculos": 30,
  "fonte": "Biblia Pastoral — Ed. Paulus",
  "versiculos": [
    {
      "number": 1,
      "text": "Grite, para ver se alguém lhe responde. A que anjo você vai recorrer?"
    },
    {
      "number": 2,
      "text": "Porque o despeito mata o insensato, e a inveja causa a morte do imbecil."
    },
    {
      "number": 3,
      "text": "Vi um insensato lançar raízes, e num momento sua casa foi amaldiçoada."
    },
    {
      "number": 4,
      "text": "Seus filhos estão longe de prosperar, são esmagados sem defensor no tribunal."
    },
    {
      "number": 5,
      "text": "- Bíblia Católica Pastoral - Ed. Paulus | Lírio Católico Jó"
    },
    {
      "number": 5,
      "text": "O faminto devorou as colheitas dele, e o sedento sugou-lhe os bens."
    },
    {
      "number": 6,
      "text": "Início da Bíblia Selecionar livro... Gênesis Êxodo Levítico Números Deuteronômio Josué Juízes Rute I Samuel II Samuel I Reis II Reis I Crônicas II Crônicas Esdras Neemias Tobias Judite Ester I Macabeus II Macabeus Jó Salmos Provérbios Eclesiastes Cântico dos Cânticos Sabedoria Eclesiástico Isaías Jeremias Lamentações Baruc Ezequiel Daniel Oséias Joel Amós Abdias Jonas Miquéias Naum Habacuc Sofonias Ageu Zacarias Malaquias São Mateus São Marcos São Lucas São João Atos dos Apóstolos Romanos I Coríntios II Coríntios Gálatas Efésios Filipenses Colossenses I Tessalonicenses II Tessalonicenses I Timóteo II Timóteo Tito Filêmon Hebreus São Tiago I São Pedro II São Pedro I São João II São João III São João São Judas Apocalipse Selecionar capítulo... Capítulo"
    },
    {
      "number": 6,
      "text": "A miséria não nasce do pó, e a fadiga não brota da terra."
    },
    {
      "number": 7,
      "text": "E o homem gera seu próprio sofrimento, como as faíscas voam para cima."
    },
    {
      "number": 8,
      "text": "Em seu lugar, eu recorreria a Deus, e poria a minha causa nas mãos dele."
    },
    {
      "number": 9,
      "text": "Ele faz coisas grandiosas e incompreensíveis, e maravilhas sem conta:"
    },
    {
      "number": 10,
      "text": "dá chuva para a terra, e rega os campos;"
    },
    {
      "number": 11,
      "text": "levanta os humildes, e concede prosperidade aos abatidos;"
    },
    {
      "number": 12,
      "text": "malogra os planos do astuto, para que as manobras deste fracassem;"
    },
    {
      "number": 13,
      "text": "apanha os espertos na astúcia deles, e desmonta as tramas do velhaco."
    },
    {
      "number": 14,
      "text": "Em pleno dia, todos esses caem nas trevas, e ao meio-dia tateiam como se fosse noite."
    },
    {
      "number": 15,
      "text": "É assim que Deus salva da língua afiada o pobre, e da mão do poderoso o necessitado."
    },
    {
      "number": 16,
      "text": "Desse modo, o fraco tem esperança, e a injustiça fecha a boca."
    },
    {
      "number": 17,
      "text": "Feliz o homem a quem Deus corrige. Portanto, não despreze a lição do Todo-poderoso."
    },
    {
      "number": 18,
      "text": "É Deus quem fere e cura a ferida, quem golpeia e cura com sua própria mão."
    },
    {
      "number": 19,
      "text": "Ele é quem liberta você de seis perigos, e no sétimo o mal não mais o atingirá."
    },
    {
      "number": 20,
      "text": "Em tempo de fome, salvará você da morte, e na guerra o protegerá do golpe da espada."
    },
    {
      "number": 21,
      "text": "Você ficará a salvo do flagelo da língua, e não temerá quando a ruína chegar."
    },
    {
      "number": 22,
      "text": "Você rirá do desastre e da fome, e não temerá os animais selvagens."
    },
    {
      "number": 23,
      "text": "Você fará aliança com os espíritos do campo, e viverá em paz com as feras."
    },
    {
      "number": 24,
      "text": "Você terá prosperidade em sua tenda e, visitando sua propriedade, verá que nada falta."
    },
    {
      "number": 25,
      "text": "Terá descendência numerosa, e seus filhos serão como erva do campo."
    },
    {
      "number": 26,
      "text": "Descerá ao túmulo em avançada velhice, como feixe de trigo colhido no tempo certo."
    },
    {
      "number": 27,
      "text": "Veja bem! Observamos tudo isso, e é coisa certa. Escute bem, e faça bom proveito”. Gerar Imagem Gerador de imagem Católica &times; Texto selecionado: Nenhum texto selecionado Configuração da Fonte: Tamanho Tipo Cor Tamanho da Fonte: 50px 20px 100px Escolha o Tipo de Fonte: Georgia Times New Roman Palatino Linotype Garamond Book Antiqua Baskerville Hoefler Text Bodoni MT Didot Cambria Playfair Display Merriweather Lora Crimson Text Libre Baskerville EB Garamond Cormorant Garamond Spectral Roboto Open Sans Lato Montserrat Poppins Raleway Nunito Work Sans Inter Quicksand Josefin Sans Arial Helvetica Trebuchet MS Verdana Tahoma Lucida Sans Calibri Century Gothic Futura Dancing Script Pacifico Great Vibes Satisfy Caveat Brush Script MT Comic Sans MS Courier New Lucida Console Monaco Consolas Source Code Pro Impact Bebas Neue Righteous Abril Fatface Cinzel Escolha entre diferentes estilos de fontes Escolha a Cor do Texto: #FFFFFF Branco Cores Rápidas Cor Personalizada Tons de Cinza Clique no seletor acima para escolher uma cor Dimensões da Imagem: Padrão (800x600) Instagram Quadrado (1080x1080) Instagram Story (1080x1350) Facebook/Twitter (1200x630) Full HD (1920x1080) Tipo de Background: Imagens Gradientes Cor Sólida Uma imagem aleatória será selecionada automaticamente Escolha um Gradiente: Roxo Profundo Índigo → Roxo Gradientes Vibrantes Gradientes Suaves Gradientes Quentes Clique no seletor acima para escolher um gradiente Escolha uma Cor Sólida: #3949AB Azul Índigo Cores Vibrantes Cores Suaves Cor Personalizada Tons de Cinza Clique no seletor acima para escolher uma cor Ou Envie sua Imagem: Escolher Arquivo Baixar Imagem Compartilhar"
    },
    {
      "number": 42,
      "text": "Ler Jo completo"
    }
  ]
}