{
  "livro": "Exodo",
  "abbrev": "ex",
  "capitulo": 1,
  "total_capitulos": 40,
  "total_versiculos": 21,
  "fonte": "Biblia Pastoral — Ed. Paulus",
  "versiculos": [
    {
      "number": 1,
      "text": "Nomes dos filhos de Israel que foram para o Egito com Jacó, cada qual com sua família:"
    },
    {
      "number": 2,
      "text": "Rúben, Simeão, Levi e Judá;"
    },
    {
      "number": 3,
      "text": "Issacar, Zabulon e Benjamim;"
    },
    {
      "number": 4,
      "text": "Dã e Neftali; Gad e Aser."
    },
    {
      "number": 5,
      "text": "Os descendentes de Jacó eram ao todo setenta pessoas. José, porém, já estava no Egito."
    },
    {
      "number": 6,
      "text": "Depois, morreu José, assim como seus irmãos e toda essa geração."
    },
    {
      "number": 7,
      "text": "Os filhos de Israel se tornavam fecundos e se multiplicavam; tornaram-se cada vez mais numerosos e poderosos, a tal ponto que o país ficou repleto deles."
    },
    {
      "number": 8,
      "text": "Subiu ao trono do Egito um novo rei que não tinha conhecido José."
    },
    {
      "number": 9,
      "text": "Ele disse ao seu povo: “Vejam! O povo dos filhos de Israel está se tornando mais numeroso e poderoso do que nós."
    },
    {
      "number": 10,
      "text": "Vamos vencê-los com astúcia, para impedir que eles se multipliquem; do contrário, em caso de guerra, eles se aliarão com o inimigo, nos atacarão e depois sairão do país”."
    },
    {
      "number": 11,
      "text": "Então impuseram sobre Israel capatazes, que os exploravam em trabalhos forçados. E assim construíram para o Faraó as cidades-armazéns de Pitom e Ramsés."
    },
    {
      "number": 12,
      "text": "Contudo, quanto mais oprimiam o povo, mais ele crescia e se multiplicava. Os filhos de Israel começaram a se tornar um pesadelo para os egípcios."
    },
    {
      "number": 13,
      "text": "Por isso, os egípcios impuseram sobre eles trabalhos duros,"
    },
    {
      "number": 14,
      "text": "e lhes amargaram a vida com dura escravidão: preparação de argila, fabricação de tijolos, vários trabalhos nos campos; enfim, com dureza os obrigaram a todos esses trabalhos."
    },
    {
      "number": 15,
      "text": "O rei do Egito ordenou às parteiras dos hebreus, que se chamavam Sefra e Fua:"
    },
    {
      "number": 16,
      "text": "“Quando vocês ajudarem as hebreias a dar à luz, observem se é meni­no ou menina: se for menino, matem; se for me­nina, deixem viver”."
    },
    {
      "number": 17,
      "text": "As parteiras, po­rém, temeram a Deus e não fizeram o que o rei do Egito lhes havia ordenado; e deixaram os meninos viver."
    },
    {
      "number": 18,
      "text": "Então o rei do Egito chamou as parteiras e lhes disse: “Por que vocês fizeram isso, deixando os meninos viver?”"
    },
    {
      "number": 19,
      "text": "Elas responderam ao Faraó: “As mulheres hebreias não são como as egípcias: são cheias de vida, e dão à luz antes que as parteiras cheguem”."
    },
    {
      "number": 20,
      "text": "Por isso, Deus favoreceu as parteiras. E o povo se multiplicou e tornou-se muito poderoso."
    },
    {
      "number": 21,
      "text": "E como as parteiras temeram a Deus, ele deu a elas uma família numerosa."
    }
  ]
}