{
  "livro": "Eclesiastes",
  "abbrev": "ec",
  "capitulo": 10,
  "total_capitulos": 12,
  "total_versiculos": 19,
  "fonte": "Biblia Pastoral — Ed. Paulus",
  "versiculos": [
    {
      "number": 1,
      "text": "Mosca morta estraga um vidro de perfume, e um pouco de insensatez pesa mais do que a sabedoria e a honra."
    },
    {
      "number": 2,
      "text": "O sábio se orienta bem, mas o insensato se desvia."
    },
    {
      "number": 3,
      "text": "Quando o insensato anda pelo caminho, falta-lhe inteligência e pensa que todo mundo é insensato também."
    },
    {
      "number": 4,
      "text": "Se a ira de um poderoso se levanta contra você, não saia do lugar, porque a calma aplaca grandes erros."
    },
    {
      "number": 5,
      "text": "Vi outro mal debaixo do sol, um erro cometido pelo soberano:"
    },
    {
      "number": 6,
      "text": "o insensato ocupando os mais altos cargos e os hábeis em posições bem inferiores."
    },
    {
      "number": 7,
      "text": "Vi escravos a cavalo, e príncipes andando a pé, como se fossem escravos."
    },
    {
      "number": 8,
      "text": "Quem cava um buraco, nele cairá. Quem derruba um muro, uma cobra o morderá."
    },
    {
      "number": 9,
      "text": "Quem carrega pedras, com elas se machuca, e quem racha lenha, corre perigo."
    },
    {
      "number": 10,
      "text": "Se o machado está cego e não for afiado, será preciso muita força; é mais vantajoso usar a sabedoria."
    },
    {
      "number": 11,
      "text": "Se a cobra não encantada morde o encantador, este não ganha nada."
    },
    {
      "number": 12,
      "text": "As palavras do sábio favorecem a ele mesmo, mas as palavras do insensato provocam sua própria ruína."
    },
    {
      "number": 13,
      "text": "Se o início das palavras do insensato já é insensatez, o fim do seu discurso será tolice perversa."
    },
    {
      "number": 14,
      "text": "O insensato multiplica as palavras, embora o homem não saiba o que vai suceder, porque ninguém lhe pode dizer o que vai acontecer no futuro."
    },
    {
      "number": 15,
      "text": "O trabalho do insensato lhe causa fadiga, pois nem sabe como ir à cidade."
    },
    {
      "number": 16,
      "text": "Ai de você, país governado por um jovem, e cujos príncipes se banqueteiam desde o amanhecer."
    },
    {
      "number": 17,
      "text": "Feliz de você, país governado por um rei nobre, e cujos príncipes comem na hora certa para se refazerem, e não para se banquetearem."
    },
    {
      "number": 18,
      "text": "Pela preguiça das mãos, o teto desaba; e por causa de braços frouxos, goteja na casa."
    },
    {
      "number": 19,
      "text": "Para se divertirem, fazem banquete, e o vinho alegra a vida: o dinheiro providencia tudo."
    }
  ]
}